torch_timeseries/__init__.py
torch_timeseries/cli/__init__.py
torch_timeseries/cli/exp.py
torch_timeseries/core/__init__.py
torch_timeseries/core/scaler.py
torch_timeseries/core/dataset/__init__.py
torch_timeseries/core/dataset/anomaly.py
torch_timeseries/core/dataset/dataset.py
torch_timeseries/core/experiments/__init__.py
torch_timeseries/core/experiments/settings.py
torch_timeseries/dataloader/__init__.py
torch_timeseries/dataloader/anomaly.py
torch_timeseries/dataloader/maskts.py
torch_timeseries/dataloader/sliding_window.py
torch_timeseries/dataloader/sliding_window_ts.py
torch_timeseries/dataloader/uea.py
torch_timeseries/dataloader/wrapper.py
torch_timeseries/dataset/ETTh1.py
torch_timeseries/dataset/ETTh2.py
torch_timeseries/dataset/ETTm1.py
torch_timeseries/dataset/ETTm2.py
torch_timeseries/dataset/Electricity.py
torch_timeseries/dataset/ExchangeRate.py
torch_timeseries/dataset/ILI.py
torch_timeseries/dataset/M4.py
torch_timeseries/dataset/MSL.py
torch_timeseries/dataset/PSM.py
torch_timeseries/dataset/SMAP.py
torch_timeseries/dataset/SMD.py
torch_timeseries/dataset/SWaT.py
torch_timeseries/dataset/SolarEnergy.py
torch_timeseries/dataset/Traffic.py
torch_timeseries/dataset/UEA.py
torch_timeseries/dataset/Weather.py
torch_timeseries/dataset/__init__.py
torch_timeseries/dataset/dummies/__init__.py
torch_timeseries/dataset/dummies/dummy.py
torch_timeseries/dataset/dummies/dummy_graph.py
torch_timeseries/experiments/Autoformer.py
torch_timeseries/experiments/CATS.py
torch_timeseries/experiments/Crossformer.py
torch_timeseries/experiments/DLinear.py
torch_timeseries/experiments/FEDformer.py
torch_timeseries/experiments/Informer.py
torch_timeseries/experiments/PatchTST.py
torch_timeseries/experiments/SCINet.py
torch_timeseries/experiments/TSMixer.py
torch_timeseries/experiments/TimesNet.py
torch_timeseries/experiments/__init__.py
torch_timeseries/experiments/anomaly_detection.py
torch_timeseries/experiments/base.py
torch_timeseries/experiments/forecast.py
torch_timeseries-0.1.5.dist-info/LICENSE
torch_timeseries-0.1.5.dist-info/METADATA
torch_timeseries-0.1.5.dist-info/WHEEL
torch_timeseries-0.1.5.dist-info/entry_points.txt
torch_timeseries-0.1.5.dist-info/top_level.txt
torch_timeseries-0.1.5.dist-info/RECORD
