Metadata-Version: 2.1
Name: torch-timeseries
Version: 0.1.5
Summary: Timeseries Learning Library for PyTorch.
Home-page: https://github.com/wayne155/pytorch_timeseries
Download-URL: https://github.com/wayne155/pytorch_timeseries/archive/0.1.5.tar.gz
Author: Weiwei Ye
Author-email: Wayne Yip <wwye155@gmail.com>
License: Apache License
Project-URL: Documentation, https://pytorch-timeseries.readthedocs.io
Project-URL: BugTracker, https://github.com/wayne155/pytorch_timeseries/issues
Keywords: deep Learning,time series,pytorch
Requires-Python: >=3.8
License-File: LICENSE
Requires-Dist: numpy
Requires-Dist: pandas
Requires-Dist: sktime
Requires-Dist: pandas>=0.29.0
Requires-Dist: scikit-learn
Requires-Dist: tqdm
Requires-Dist: einops
Requires-Dist: prettytable
Requires-Dist: torchmetrics==1.1.1
Requires-Dist: fire>=0.5.0
Provides-Extra: g
Requires-Dist: pyg; extra == "g"
